mapant
