Metadata-Version: 1.1
Name: mapant
Version: 0.0.3
Summary: Create custom maps for GARMIN GPS from mapant
Home-page: https://github.com/trygveasp/mapant
Author: Trygve Aspelien
Author-email: trygve@aspelien.no
License: UNKNOWN
Keywords: custom maps,mapant,garmin,gps,utm
Platform: UNKNOWN
Classifier: Development Status :: 4 - Beta
Classifier: Programming Language :: Python :: 3.5
Classifier: Programming Language :: Python :: 3.6
Classifier: Programming Language :: Python :: 3.7
